samplingsimulatorpy/__init__.py
samplingsimulatorpy/draw_samples.py
samplingsimulatorpy/generate_virtual_pop.py
samplingsimulatorpy/plot_sample_hist.py
samplingsimulatorpy/plot_sampling_hist.py
samplingsimulatorpy/samplingsimulatorpy.py
samplingsimulatorpy/stat_summary.py
samplingsimulatorpy-0.1.0.dist-info/LICENSE
samplingsimulatorpy-0.1.0.dist-info/WHEEL
samplingsimulatorpy-0.1.0.dist-info/METADATA
samplingsimulatorpy-0.1.0.dist-info/RECORD
