Metadata-Version: 2.1
Name: samplingsimulatorpy
Version: 0.1.0
Summary: This is a sampling simulator
Home-page: https://github.com/UBC-MDS/samplingsimulatorpy
License: MIT
Author: Your Name
Author-email: you@example.com
Requires-Python: >=3.7,<4.0
Classifier: License :: OSI Approved :: MIT License
Classifier: Programming Language :: Python :: 3
Classifier: Programming Language :: Python :: 3.7
Classifier: Programming Language :: Python :: 3.8
Requires-Dist: altair (>=3.3.0)
Requires-Dist: numpy (>=1.18.1,<2.0.0)
Requires-Dist: pandas (>=1.0.1,<2.0.0)
Project-URL: Documentation, https://samplingsimulatorpy.readthedocs.io
Project-URL: Repository, https://github.com/UBC-MDS/samplingsimulatorpy
